README.md
setup.py
youtube_api/__init__.py
youtube_api/parsers.py
youtube_api/youtube_api.py
youtube_api/youtube_api_utils.py
ytda.egg-info/PKG-INFO
ytda.egg-info/SOURCES.txt
ytda.egg-info/dependency_links.txt
ytda.egg-info/requires.txt
ytda.egg-info/top_level.txt