Metadata-Version: 2.1
Name: ytda
Version: 0.0.18
Summary: ytda is a Python wrapper for the YouTube Data API.
Home-page: https://github.com/m4rkohr/youtube-data-api
Author: Leon Yin, Megan Brown, M4rkoHR
License: MIT
Keywords: youtube-data-api youtube-data youtube-api wrapper youtube tweepy social-media
Platform: UNKNOWN
Classifier: Programming Language :: Python :: 3
Classifier: License :: OSI Approved :: MIT License
Classifier: Operating System :: OS Independent
